main/__init__.py
main/pic.py
giteebed-1.0.1.dist-info/LICENSE
giteebed-1.0.1.dist-info/METADATA
giteebed-1.0.1.dist-info/WHEEL
giteebed-1.0.1.dist-info/top_level.txt
giteebed-1.0.1.dist-info/RECORD
