Metadata-Version: 2.1
Name: giteebed
Version: 1.0.1
Summary: A image bed based on gitee
Home-page: https://github.com/fogsong233/gitee-bed
Author: fogsong
Author-email: 2031602579@qq.com
License: Apache License
Keywords: A image bed based on gitee
Platform: any
Requires-Dist: requests
